setup.py
gmail/__init__.py
gmail/email.py
gmail/fib.py
ljf7_gmail.egg-info/PKG-INFO
ljf7_gmail.egg-info/SOURCES.txt
ljf7_gmail.egg-info/dependency_links.txt
ljf7_gmail.egg-info/top_level.txt