Metadata-Version: 2.1
Name: ljf7-gmail
Version: 151
Summary: To solve fib by recursion
Author: Linus Trovalds
